[ {
  "duration" : 0.010559999995166436,
  "eventName" : "sdk:pre-test",
  "startTime" : 187124.250036,
  "success" : true,
  "worker" : 1,
  "failure" : null,
  "details" : null,
  "entryType" : "measure",
  "platform" : 0,
  "command" : null,
  "testName" : null,
  "hookType" : ""
}, {
  "duration" : 0.010559999995166436,
  "eventName" : "sdk:post-test",
  "startTime" : 215252.834027,
  "success" : true,
  "worker" : 1,
  "failure" : null,
  "details" : null,
  "entryType" : "measure",
  "platform" : 0,
  "command" : null,
  "testName" : null,
  "hookType" : ""
}, {
  "duration" : 0.014577999943867326,
  "eventName" : "sdk:pre-test",
  "startTime" : 889836.909522,
  "success" : true,
  "worker" : 1,
  "failure" : null,
  "details" : null,
  "entryType" : "measure",
  "platform" : 0,
  "command" : null,
  "testName" : null,
  "hookType" : ""
}, {
  "duration" : 0.005040000076405704,
  "eventName" : "sdk:post-test",
  "startTime" : 914494.379048,
  "success" : true,
  "worker" : 1,
  "failure" : null,
  "details" : null,
  "entryType" : "measure",
  "platform" : 0,
  "command" : null,
  "testName" : null,
  "hookType" : ""
}, {
  "duration" : 0.04795200005173683,
  "eventName" : "sdk:pre-test",
  "startTime" : 1272488.295518,
  "success" : true,
  "worker" : 1,
  "failure" : null,
  "details" : null,
  "entryType" : "measure",
  "platform" : 0,
  "command" : null,
  "testName" : null,
  "hookType" : ""
}, {
  "duration" : 0.006623000139370561,
  "eventName" : "sdk:post-test",
  "startTime" : 1290870.187427,
  "success" : true,
  "worker" : 1,
  "failure" : null,
  "details" : null,
  "entryType" : "measure",
  "platform" : 0,
  "command" : null,
  "testName" : null,
  "hookType" : ""
}, {
  "duration" : 0.015901000006124377,
  "eventName" : "sdk:pre-test",
  "startTime" : 1349821.68607,
  "success" : true,
  "worker" : 1,
  "failure" : null,
  "details" : null,
  "entryType" : "measure",
  "platform" : 0,
  "command" : null,
  "testName" : null,
  "hookType" : ""
}, {
  "duration" : 0.005190000170841813,
  "eventName" : "sdk:post-test",
  "startTime" : 1367272.740575,
  "success" : true,
  "worker" : 1,
  "failure" : null,
  "details" : null,
  "entryType" : "measure",
  "platform" : 0,
  "command" : null,
  "testName" : null,
  "hookType" : ""
}, {
  "duration" : 0.012644999893382192,
  "eventName" : "sdk:pre-test",
  "startTime" : 1528947.544591,
  "success" : true,
  "worker" : 1,
  "failure" : null,
  "details" : null,
  "entryType" : "measure",
  "platform" : 0,
  "command" : null,
  "testName" : null,
  "hookType" : ""
}, {
  "duration" : 0.004398000193759799,
  "eventName" : "sdk:post-test",
  "startTime" : 1543752.855512,
  "success" : true,
  "worker" : 1,
  "failure" : null,
  "details" : null,
  "entryType" : "measure",
  "platform" : 0,
  "command" : null,
  "testName" : null,
  "hookType" : ""
}, {
  "duration" : 0.013174999970942736,
  "eventName" : "sdk:pre-test",
  "startTime" : 1659889.411358,
  "success" : true,
  "worker" : 1,
  "failure" : null,
  "details" : null,
  "entryType" : "measure",
  "platform" : 0,
  "command" : null,
  "testName" : null,
  "hookType" : ""
}, {
  "duration" : 0.005430000135675073,
  "eventName" : "sdk:post-test",
  "startTime" : 1679798.592795,
  "success" : true,
  "worker" : 1,
  "failure" : null,
  "details" : null,
  "entryType" : "measure",
  "platform" : 0,
  "command" : null,
  "testName" : null,
  "hookType" : ""
}, {
  "duration" : 0.018616000190377235,
  "eventName" : "sdk:pre-test",
  "startTime" : 2682295.840304,
  "success" : true,
  "worker" : 1,
  "failure" : null,
  "details" : null,
  "entryType" : "measure",
  "platform" : 0,
  "command" : null,
  "testName" : null,
  "hookType" : ""
}, {
  "duration" : 0.004759000148624182,
  "eventName" : "sdk:post-test",
  "startTime" : 2703888.082811,
  "success" : true,
  "worker" : 1,
  "failure" : null,
  "details" : null,
  "entryType" : "measure",
  "platform" : 0,
  "command" : null,
  "testName" : null,
  "hookType" : ""
}, {
  "duration" : 0.029587000142782927,
  "eventName" : "sdk:pre-test",
  "startTime" : 2715880.336857,
  "success" : true,
  "worker" : 1,
  "failure" : null,
  "details" : null,
  "entryType" : "measure",
  "platform" : 0,
  "command" : null,
  "testName" : null,
  "hookType" : ""
}, {
  "duration" : 0.0043579996563494205,
  "eventName" : "sdk:post-test",
  "startTime" : 2733325.064658,
  "success" : true,
  "worker" : 1,
  "failure" : null,
  "details" : null,
  "entryType" : "measure",
  "platform" : 0,
  "command" : null,
  "testName" : null,
  "hookType" : ""
}, {
  "duration" : 0.016851999796926975,
  "eventName" : "sdk:pre-test",
  "startTime" : 2753318.94588,
  "success" : true,
  "worker" : 1,
  "failure" : null,
  "details" : null,
  "entryType" : "measure",
  "platform" : 0,
  "command" : null,
  "testName" : null,
  "hookType" : ""
}, {
  "duration" : 0.0049690003506839275,
  "eventName" : "sdk:post-test",
  "startTime" : 2769916.075876,
  "success" : true,
  "worker" : 1,
  "failure" : null,
  "details" : null,
  "entryType" : "measure",
  "platform" : 0,
  "command" : null,
  "testName" : null,
  "hookType" : ""
}, {
  "duration" : 0.013735999818891287,
  "eventName" : "sdk:pre-test",
  "startTime" : 2784592.451638,
  "success" : true,
  "worker" : 1,
  "failure" : null,
  "details" : null,
  "entryType" : "measure",
  "platform" : 0,
  "command" : null,
  "testName" : null,
  "hookType" : ""
}, {
  "duration" : 0.016552000306546688,
  "eventName" : "sdk:post-test",
  "startTime" : 2802295.322814,
  "success" : true,
  "worker" : 1,
  "failure" : null,
  "details" : null,
  "entryType" : "measure",
  "platform" : 0,
  "command" : null,
  "testName" : null,
  "hookType" : ""
}, {
  "duration" : 0.01408699993044138,
  "eventName" : "sdk:pre-test",
  "startTime" : 3297802.42368,
  "success" : true,
  "worker" : 1,
  "failure" : null,
  "details" : null,
  "entryType" : "measure",
  "platform" : 0,
  "command" : null,
  "testName" : null,
  "hookType" : ""
}, {
  "duration" : 0.03158100042492151,
  "eventName" : "sdk:pre-test",
  "startTime" : 3364255.271132,
  "success" : true,
  "worker" : 1,
  "failure" : null,
  "details" : null,
  "entryType" : "measure",
  "platform" : 0,
  "command" : null,
  "testName" : null,
  "hookType" : ""
}, {
  "duration" : 0.019737000111490488,
  "eventName" : "sdk:pre-test",
  "startTime" : 3408356.650604,
  "success" : true,
  "worker" : 1,
  "failure" : null,
  "details" : null,
  "entryType" : "measure",
  "platform" : 0,
  "command" : null,
  "testName" : null,
  "hookType" : ""
}, {
  "duration" : 0.0049600000493228436,
  "eventName" : "sdk:post-test",
  "startTime" : 3427588.710129,
  "success" : true,
  "worker" : 1,
  "failure" : null,
  "details" : null,
  "entryType" : "measure",
  "platform" : 0,
  "command" : null,
  "testName" : null,
  "hookType" : ""
}, {
  "duration" : 0.015409999992698431,
  "eventName" : "sdk:pre-test",
  "startTime" : 3449637.266899,
  "success" : true,
  "worker" : 1,
  "failure" : null,
  "details" : null,
  "entryType" : "measure",
  "platform" : 0,
  "command" : null,
  "testName" : null,
  "hookType" : ""
}, {
  "duration" : 0.014919000212103128,
  "eventName" : "sdk:pre-test",
  "startTime" : 3478025.816549,
  "success" : true,
  "worker" : 1,
  "failure" : null,
  "details" : null,
  "entryType" : "measure",
  "platform" : 0,
  "command" : null,
  "testName" : null,
  "hookType" : ""
}, {
  "duration" : 0.006171999964863062,
  "eventName" : "sdk:post-test",
  "startTime" : 3527530.782029,
  "success" : true,
  "worker" : 1,
  "failure" : null,
  "details" : null,
  "entryType" : "measure",
  "platform" : 0,
  "command" : null,
  "testName" : null,
  "hookType" : ""
}, {
  "duration" : 0.01835600007325411,
  "eventName" : "sdk:pre-test",
  "startTime" : 3554685.882776,
  "success" : true,
  "worker" : 1,
  "failure" : null,
  "details" : null,
  "entryType" : "measure",
  "platform" : 0,
  "command" : null,
  "testName" : null,
  "hookType" : ""
}, {
  "duration" : 0.004468999803066254,
  "eventName" : "sdk:post-test",
  "startTime" : 3639719.55181,
  "success" : true,
  "worker" : 1,
  "failure" : null,
  "details" : null,
  "entryType" : "measure",
  "platform" : 0,
  "command" : null,
  "testName" : null,
  "hookType" : ""
}, {
  "duration" : 0.016732000280171633,
  "eventName" : "sdk:pre-test",
  "startTime" : 3666859.648288,
  "success" : true,
  "worker" : 1,
  "failure" : null,
  "details" : null,
  "entryType" : "measure",
  "platform" : 0,
  "command" : null,
  "testName" : null,
  "hookType" : ""
}, {
  "duration" : 0.005609999876469374,
  "eventName" : "sdk:post-test",
  "startTime" : 3681086.991586,
  "success" : true,
  "worker" : 1,
  "failure" : null,
  "details" : null,
  "entryType" : "measure",
  "platform" : 0,
  "command" : null,
  "testName" : null,
  "hookType" : ""
}, {
  "duration" : 0.013425999786704779,
  "eventName" : "sdk:pre-test",
  "startTime" : 3814456.496755,
  "success" : true,
  "worker" : 1,
  "failure" : null,
  "details" : null,
  "entryType" : "measure",
  "platform" : 0,
  "command" : null,
  "testName" : null,
  "hookType" : ""
}, {
  "duration" : 0.004900000058114529,
  "eventName" : "sdk:post-test",
  "startTime" : 3824727.427844,
  "success" : true,
  "worker" : 1,
  "failure" : null,
  "details" : null,
  "entryType" : "measure",
  "platform" : 0,
  "command" : null,
  "testName" : null,
  "hookType" : ""
}, {
  "duration" : 0.016210999805480242,
  "eventName" : "sdk:pre-test",
  "startTime" : 3838860.897231,
  "success" : true,
  "worker" : 1,
  "failure" : null,
  "details" : null,
  "entryType" : "measure",
  "platform" : 0,
  "command" : null,
  "testName" : null,
  "hookType" : ""
}, {
  "duration" : 0.006062000058591366,
  "eventName" : "sdk:post-test",
  "startTime" : 3854931.727151,
  "success" : true,
  "worker" : 1,
  "failure" : null,
  "details" : null,
  "entryType" : "measure",
  "platform" : 0,
  "command" : null,
  "testName" : null,
  "hookType" : ""
} ]